[{"code":"11","name":"서울특별시","children":[]},{"code":"26","name":"부산광역시","children":[]},{"code":"27","name":"대구광역시","children":[]},{"code":"28","name":"인천광역시","children":[]},{"code":"29","name":"광주광역시","children":[]},{"code":"30","name":"대전광역시","children":[]},{"code":"31","name":"울산광역시","children":[]},{"code":"41","name":"경기도","children":[]},{"code":"42","name":"강원도","children":[]},{"code":"43","name":"충청북도","children":[]},{"code":"44","name":"충청남도","children":[]},{"code":"45","name":"전라북도","children":[]},{"code":"46","name":"전라남도","children":[]},{"code":"47","name":"경상북도","children":[]},{"code":"48","name":"경상남도","children":[]},{"code":"49","name":"제주특별자치도","children":[]},{"code":"50","name":"세종특별자치시","children":[]}]